[
  {
    "name": "Template 1",
    "positions": [0, 1, 2, 3, 4, 5, 6, 7, 8, 9, 10, 11, 12, 13, 14, 15, 16, 17, 18, 19, 20],
    "PLSL": 0,
    "PLSR": 0,
    "PLWR": 0,
    "PRWR": 0,
    "PLBB": 0,
    "PRBB": 0,
    "PLFB": 0,
    "PRFB": 0
  },
  {
    "name": "Template 2",
    "positions": [1, 3, 4, 13, 14, 15, 16, 17, 18],
    "PLSL": 0,
    "PLSR": 0,
    "PLWR": 1,
    "PRWR": 1,
    "PLBB": 0,
    "PRBB": 0,
    "PLFB": 0,
    "PRFB": 0
  },
  {
    "name": "Template 3",
    "positions": [1, 3, 4, 13, 14, 15, 16, 17, 18],
    "PLSL": 0,
    "PLSR": 0,
    "PLWR": 1,
    "PRWR": 1,
    "PLBB": 1,
    "PRBB": 1,
    "PLFB": 1,
    "PRFB": 1
  },
  {
    "name": "Template 4",
    "positions": [1, 3, 4, 13, 14, 15, 16, 17, 18],
    "PLSL": 0,
    "PLSR": 0,
    "PLWR": 1,
    "PRWR": 1,
    "PLBB": 3,
    "PRBB": 3,
    "PLFB": 3,
    "PRFB": 3
  },
  {
    "name": "Template 5",
    "positions": [1, 3, 4, 13, 14, 15, 16, 17, 18],
    "PLSL": 0,
    "PLSR": 0,
    "PLWR": 3,
    "PRWR": 3,
    "PLBB": 0,
    "PRBB": 0,
    "PLFB": 0,
    "PRFB": 0
  },
  {
    "name": "Template 6",
    "positions": [1, 3, 4, 13, 14, 15, 16, 17, 18],
    "PLSL": 0,
    "PLSR": 0,
    "PLWR": 3,
    "PRWR": 3,
    "PLBB": 1,
    "PRBB": 1,
    "PLFB": 1,
    "PRFB": 1
  },
  {
    "name": "Template 7",
    "positions": [1, 3, 4, 13, 14, 15, 16, 17, 18],
    "PLSL": 0,
    "PLSR": 0,
    "PLWR": 3,
    "PRWR": 3,
    "PLBB": 3,
    "PRBB": 3,
    "PLFB": 3,
    "PRFB": 3
  },
  {
    "name": "Template 8",
    "positions": [0, 1, 2, 3, 4, 10, 11, 12, 13, 14, 15, 16, 17, 18, 19, 20],
    "PLSL": 0,
    "PLSR": 1,
    "PLWR": 1,
    "PRWR": 1,
    "PLBB": 0,
    "PRBB": 0,
    "PLFB": 0,
    "PRFB": 0
  },
  {
    "name": "Template 9",
    "positions": [1, 3, 4, 10, 11, 13, 14, 15, 16, 17, 18],
    "PLSL": 0,
    "PLSR": 1,
    "PLWR": 1,
    "PRWR": 1,
    "PLBB": 1,
    "PRBB": 0,
    "PLFB": 1,
    "PRFB": 0
  },
  {
    "name": "Template 10",
    "positions": [1, 3, 4, 10, 11, 13, 14, 15, 16, 17, 18],
    "PLSL": 0,
    "PLSR": 1,
    "PLWR": 1,
    "PRWR": 1,
    "PLBB": 3,
    "PRBB": 0,
    "PLFB": 3,
    "PRFB": 0
  },
  {
    "name": "Template 11",
    "positions": [0, 1, 2, 3, 4, 10, 11, 12, 13, 14, 15, 16, 17, 18, 19, 20],
    "PLSL": 0,
    "PLSR": 1,
    "PLWR": 3,
    "PRWR": 3,
    "PLBB": 0,
    "PRBB": 0,
    "PLFB": 0,
    "PRFB": 0
  },
  {
    "name": "Template 12",
    "positions": [1, 3, 4, 10, 11, 13, 14, 15, 16, 17, 18],
    "PLSL": 0,
    "PLSR": 1,
    "PLWR": 3,
    "PRWR": 3,
    "PLBB": 1,
    "PRBB": 0,
    "PLFB": 1,
    "PRFB": 0
  },
  {
    "name": "Template 13",
    "positions": [1, 3, 4, 10, 11, 13, 14, 15, 16, 17, 18],
    "PLSL": 0,
    "PLSR": 1,
    "PLWR": 3,
    "PRWR": 3,
    "PLBB": 3,
    "PRBB": 0,
    "PLFB": 3,
    "PRFB": 0
  },
  {
    "name": "Template 14",
    "positions": [0, 1, 2, 3, 4, 10, 11, 12, 13, 14, 15, 16, 17, 18, 19, 20],
    "PLSL": 0,
    "PLSR": 1,
    "PLWR": 10,
    "PRWR": 10,
    "PLBB": 0,
    "PRBB": 0,
    "PLFB": 0,
    "PRFB": 0
  },
  {
    "name": "Template 15",
    "positions": [1, 3, 4, 10, 11, 13, 14, 15, 16, 17, 18],
    "PLSL": 0,
    "PLSR": 1,
    "PLWR": 10,
    "PRWR": 10,
    "PLBB": 1,
    "PRBB": 0,
    "PLFB": 1,
    "PRFB": 0
  },
  {
    "name": "Template 16",
    "positions": [1, 3, 4, 10, 11, 13, 14, 15, 16, 17, 18],
    "PLSL": 0,
    "PLSR": 1,
    "PLWR": 10,
    "PRWR": 10,
    "PLBB": 3,
    "PRBB": 0,
    "PLFB": 3,
    "PRFB": 0
  },
  {
    "name": "Template 17",
    "positions": [0, 1, 2, 3, 4, 10, 11, 12, 13, 14, 15, 16, 17, 18, 19, 20],
    "PLSL": 0,
    "PLSR": 1,
    "PLWR": 11,
    "PRWR": 11,
    "PLBB": 0,
    "PRBB": 0,
    "PLFB": 0,
    "PRFB": 0
  },
  {
    "name": "Template 18",
    "positions": [1, 3, 4, 10, 11, 13, 14, 15, 16, 17, 18],
    "PLSL": 0,
    "PLSR": 1,
    "PLWR": 11,
    "PRWR": 11,
    "PLBB": 1,
    "PRBB": 0,
    "PLFB": 1,
    "PRFB": 0
  },
  {
    "name": "Template 19",
    "positions": [1, 3, 4, 10, 11, 13, 14, 15, 16, 17, 18],
    "PLSL": 0,
    "PLSR": 1,
    "PLWR": 11,
    "PRWR": 11,
    "PLBB": 3,
    "PRBB": 0,
    "PLFB": 3,
    "PRFB": 0
  },
  {
    "name": "Template 20",
    "positions": [0, 1, 2, 3, 4, 10, 11, 12, 13, 14, 15, 16, 17, 18, 19, 20],
    "PLSL": 0,
    "PLSR": 3,
    "PLWR": 1,
    "PRWR": 1,
    "PLBB": 0,
    "PRBB": 0,
    "PLFB": 0,
    "PRFB": 0
  },
  {
    "name": "Template 21",
    "positions": [1, 3, 4, 10, 11, 13, 14, 15, 16, 17, 18],
    "PLSL": 0,
    "PLSR": 3,
    "PLWR": 1,
    "PRWR": 1,
    "PLBB": 1,
    "PRBB": 0,
    "PLFB": 1,
    "PRFB": 0
  },
  {
    "name": "Template 22",
    "positions": [1, 3, 4, 10, 11, 13, 14, 15, 16, 17, 18],
    "PLSL": 0,
    "PLSR": 3,
    "PLWR": 1,
    "PRWR": 1,
    "PLBB": 3,
    "PRBB": 0,
    "PLFB": 3,
    "PRFB": 0
  },
  {
    "name": "Template 23",
    "positions": [0, 1, 2, 3, 4, 10, 11, 12, 13, 14, 15, 16, 17, 18, 19, 20],
    "PLSL": 0,
    "PLSR": 3,
    "PLWR": 3,
    "PRWR": 3,
    "PLBB": 0,
    "PRBB": 0,
    "PLFB": 0,
    "PRFB": 0
  },
  {
    "name": "Template 24",
    "positions": [1, 3, 4, 10, 11, 13, 14, 15, 16, 17, 18],
    "PLSL": 0,
    "PLSR": 3,
    "PLWR": 3,
    "PRWR": 3,
    "PLBB": 1,
    "PRBB": 0,
    "PLFB": 1,
    "PRFB": 0
  },
  {
    "name": "Template 25",
    "positions": [1, 3, 4, 10, 11, 13, 14, 15, 16, 17, 18],
    "PLSL": 0,
    "PLSR": 3,
    "PLWR": 3,
    "PRWR": 3,
    "PLBB": 3,
    "PRBB": 0,
    "PLFB": 3,
    "PRFB": 0
  },
  {
    "name": "Template 26",
    "positions": [0, 1, 2, 3, 4, 10, 11, 12, 13, 14, 15, 16, 17, 18, 19, 20],
    "PLSL": 0,
    "PLSR": 3,
    "PLWR": 10,
    "PRWR": 10,
    "PLBB": 0,
    "PRBB": 0,
    "PLFB": 0,
    "PRFB": 0
  },
  {
    "name": "Template 27",
    "positions": [1, 3, 4, 10, 11, 13, 14, 15, 16, 17, 18],
    "PLSL": 0,
    "PLSR": 3,
    "PLWR": 10,
    "PRWR": 10,
    "PLBB": 1,
    "PRBB": 0,
    "PLFB": 1,
    "PRFB": 0
  },
  {
    "name": "Template 28",
    "positions": [1, 3, 4, 10, 11, 13, 14, 15, 16, 17, 18],
    "PLSL": 0,
    "PLSR": 3,
    "PLWR": 10,
    "PRWR": 10,
    "PLBB": 3,
    "PRBB": 0,
    "PLFB": 3,
    "PRFB": 0
  },
  {
    "name": "Template 29",
    "positions": [0, 1, 2, 3, 4, 10, 11, 12, 13, 14, 15, 16, 17, 18, 19, 20],
    "PLSL": 0,
    "PLSR": 3,
    "PLWR": 11,
    "PRWR": 11,
    "PLBB": 0,
    "PRBB": 0,
    "PLFB": 0,
    "PRFB": 0
  },
  {
    "name": "Template 30",
    "positions": [1, 3, 4, 10, 11, 13, 14, 15, 16, 17, 18],
    "PLSL": 0,
    "PLSR": 3,
    "PLWR": 11,
    "PRWR": 11,
    "PLBB": 1,
    "PRBB": 0,
    "PLFB": 1,
    "PRFB": 0
  },
  {
    "name": "Template 31",
    "positions": [1, 3, 4, 10, 11, 13, 14, 15, 16, 17, 18],
    "PLSL": 0,
    "PLSR": 3,
    "PLWR": 11,
    "PRWR": 11,
    "PLBB": 3,
    "PRBB": 0,
    "PLFB": 3,
    "PRFB": 0
  },
  {
    "name": "Template 32",
    "positions": [0, 1, 2, 3, 4, 10, 11, 12, 13, 14, 15, 16, 17, 18, 19, 20],
    "PLSL": 1,
    "PLSR": 0,
    "PLWR": 1,
    "PRWR": 1,
    "PLBB": 0,
    "PRBB": 0,
    "PLFB": 0,
    "PRFB": 0
  },
  {
    "name": "Template 33",
    "positions": [1, 3, 4, 10, 11, 13, 14, 15, 16, 17, 18],
    "PLSL": 1,
    "PLSR": 0,
    "PLWR": 1,
    "PRWR": 1,
    "PLBB": 0,
    "PRBB": 1,
    "PLFB": 0,
    "PRFB": 1
  },
  {
    "name": "Template 34",
    "positions": [1, 3, 4, 10, 11, 13, 14, 15, 16, 17, 18],
    "PLSL": 1,
    "PLSR": 0,
    "PLWR": 1,
    "PRWR": 1,
    "PLBB": 0,
    "PRBB": 3,
    "PLFB": 0,
    "PRFB": 3
  },
  {
    "name": "Template 35",
    "positions": [0, 1, 2, 3, 4, 10, 11, 12, 13, 14, 15, 16, 17, 18, 19, 20],
    "PLSL": 1,
    "PLSR": 0,
    "PLWR": 3,
    "PRWR": 3,
    "PLBB": 0,
    "PRBB": 0,
    "PLFB": 0,
    "PRFB": 0
  },
  {
    "name": "Template 36",
    "positions": [1, 3, 4, 10, 11, 13, 14, 15, 16, 17, 18],
    "PLSL": 1,
    "PLSR": 0,
    "PLWR": 3,
    "PRWR": 3,
    "PLBB": 0,
    "PRBB": 1,
    "PLFB": 0,
    "PRFB": 1
  },
  {
    "name": "Template 37",
    "positions": [1, 3, 4, 10, 11, 13, 14, 15, 16, 17, 18],
    "PLSL": 1,
    "PLSR": 0,
    "PLWR": 3,
    "PRWR": 3,
    "PLBB": 0,
    "PRBB": 3,
    "PLFB": 0,
    "PRFB": 3
  },
  {
    "name": "Template 38",
    "positions": [0, 1, 2, 3, 4, 10, 11, 12, 13, 14, 15, 16, 17, 18, 19, 20],
    "PLSL": 1,
    "PLSR": 0,
    "PLWR": 10,
    "PRWR": 10,
    "PLBB": 0,
    "PRBB": 0,
    "PLFB": 0,
    "PRFB": 0
  },
  {
    "name": "Template 39",
    "positions": [1, 3, 4, 10, 11, 13, 14, 15, 16, 17, 18],
    "PLSL": 1,
    "PLSR": 0,
    "PLWR": 10,
    "PRWR": 10,
    "PLBB": 0,
    "PRBB": 1,
    "PLFB": 0,
    "PRFB": 1
  },
  {
    "name": "Template 40",
    "positions": [1, 3, 4, 10, 11, 13, 14, 15, 16, 17, 18],
    "PLSL": 1,
    "PLSR": 0,
    "PLWR": 10,
    "PRWR": 10,
    "PLBB": 0,
    "PRBB": 3,
    "PLFB": 0,
    "PRFB": 3
  },
  {
    "name": "Template 41",
    "positions": [0, 1, 2, 3, 4, 10, 11, 12, 13, 14, 15, 16, 17, 18, 19, 20],
    "PLSL": 1,
    "PLSR": 0,
    "PLWR": 11,
    "PRWR": 11,
    "PLBB": 0,
    "PRBB": 0,
    "PLFB": 0,
    "PRFB": 0
  },
  {
    "name": "Template 42",
    "positions": [1, 3, 4, 10, 11, 13, 14, 15, 16, 17, 18],
    "PLSL": 1,
    "PLSR": 0,
    "PLWR": 11,
    "PRWR": 11,
    "PLBB": 0,
    "PRBB": 1,
    "PLFB": 0,
    "PRFB": 1
  },
  {
    "name": "Template 43",
    "positions": [1, 3, 4, 10, 11, 13, 14, 15, 16, 17, 18],
    "PLSL": 1,
    "PLSR": 0,
    "PLWR": 11,
    "PRWR": 11,
    "PLBB": 0,
    "PRBB": 3,
    "PLFB": 0,
    "PRFB": 3
  },
  {
    "name": "Template 44",
    "positions": [0, 1, 2, 3, 4, 10, 11, 12, 13, 14, 15, 16, 17, 18, 19, 20],
    "PLSL": 3,
    "PLSR": 0,
    "PLWR": 1,
    "PRWR": 1,
    "PLBB": 0,
    "PRBB": 0,
    "PLFB": 0,
    "PRFB": 0
  },
  {
    "name": "Template 45",
    "positions": [1, 3, 4, 10, 11, 13, 14, 15, 16, 17, 18],
    "PLSL": 3,
    "PLSR": 0,
    "PLWR": 1,
    "PRWR": 1,
    "PLBB": 0,
    "PRBB": 1,
    "PLFB": 0,
    "PRFB": 1
  },
  {
    "name": "Template 46",
    "positions": [1, 3, 4, 10, 11, 13, 14, 15, 16, 17, 18],
    "PLSL": 3,
    "PLSR": 0,
    "PLWR": 1,
    "PRWR": 1,
    "PLBB": 0,
    "PRBB": 3,
    "PLFB": 0,
    "PRFB": 3
  },
  {
    "name": "Template 47",
    "positions": [0, 1, 2, 3, 4, 10, 11, 12, 13, 14, 15, 16, 17, 18, 19, 20],
    "PLSL": 3,
    "PLSR": 0,
    "PLWR": 3,
    "PRWR": 3,
    "PLBB": 0,
    "PRBB": 0,
    "PLFB": 0,
    "PRFB": 0
  },
  {
    "name": "Template 48",
    "positions": [1, 3, 4, 10, 11, 13, 14, 15, 16, 17, 18],
    "PLSL": 3,
    "PLSR": 0,
    "PLWR": 3,
    "PRWR": 3,
    "PLBB": 0,
    "PRBB": 1,
    "PLFB": 0,
    "PRFB": 1
  },
  {
    "name": "Template 49",
    "positions": [1, 3, 4, 10, 11, 13, 14, 15, 16, 17, 18],
    "PLSL": 3,
    "PLSR": 0,
    "PLWR": 3,
    "PRWR": 3,
    "PLBB": 0,
    "PRBB": 3,
    "PLFB": 0,
    "PRFB": 3
  },
  {
    "name": "Template 50",
    "positions": [0, 1, 2, 3, 4, 10, 11, 12, 13, 14, 15, 16, 17, 18, 19, 20],
    "PLSL": 3,
    "PLSR": 0,
    "PLWR": 10,
    "PRWR": 10,
    "PLBB": 0,
    "PRBB": 0,
    "PLFB": 0,
    "PRFB": 0
  },
  {
    "name": "Template 51",
    "positions": [1, 3, 4, 10, 11, 13, 14, 15, 16, 17, 18],
    "PLSL": 3,
    "PLSR": 0,
    "PLWR": 10,
    "PRWR": 10,
    "PLBB": 0,
    "PRBB": 1,
    "PLFB": 0,
    "PRFB": 1
  },
  {
    "name": "Template 52",
    "positions": [1, 3, 4, 10, 11, 13, 14, 15, 16, 17, 18],
    "PLSL": 3,
    "PLSR": 0,
    "PLWR": 10,
    "PRWR": 10,
    "PLBB": 0,
    "PRBB": 3,
    "PLFB": 0,
    "PRFB": 3
  },
  {
    "name": "Template 53",
    "positions": [0, 1, 2, 3, 4, 10, 11, 12, 13, 14, 15, 16, 17, 18, 19, 20],
    "PLSL": 3,
    "PLSR": 0,
    "PLWR": 11,
    "PRWR": 11,
    "PLBB": 0,
    "PRBB": 0,
    "PLFB": 0,
    "PRFB": 0
  },
  {
    "name": "Template 54",
    "positions": [1, 3, 4, 10, 11, 13, 14, 15, 16, 17, 18],
    "PLSL": 3,
    "PLSR": 0,
    "PLWR": 11,
    "PRWR": 11,
    "PLBB": 0,
    "PRBB": 1,
    "PLFB": 0,
    "PRFB": 1
  },
  {
    "name": "Template 55",
    "positions": [1, 3, 4, 10, 11, 13, 14, 15, 16, 17, 18],
    "PLSL": 3,
    "PLSR": 0,
    "PLWR": 11,
    "PRWR": 11,
    "PLBB": 0,
    "PRBB": 3,
    "PLFB": 0,
    "PRFB": 3
  },
  {
    "name": "Template 56",
    "positions": [0, 1, 3, 4, 10, 11, 12],
    "PLSL": 1,
    "PLSR": 1,
    "PLWR": 0,
    "PRWR": 0,
    "PLBB": 0,
    "PRBB": 0,
    "PLFB": 0,
    "PRFB": 0
  },
  {
    "name": "Template 57",
    "positions": [0, 1, 3, 4, 10, 11, 12],
    "PLSL": 1,
    "PLSR": 1,
    "PLWR": 1,
    "PRWR": 1,
    "PLBB": 0,
    "PRBB": 0,
    "PLFB": 0,
    "PRFB": 0
  },
  {
    "name": "Template 58",
    "positions": [0, 1, 3, 4, 10, 11, 12],
    "PLSL": 1,
    "PLSR": 1,
    "PLWR": 10,
    "PRWR": 10,
    "PLBB": 0,
    "PRBB": 0,
    "PLFB": 0,
    "PRFB": 0
  },
  {
    "name": "Template 59",
    "positions": [0, 1, 3, 4, 10, 11, 12],
    "PLSL": 1,
    "PLSR": 1,
    "PLWR": 11,
    "PRWR": 11,
    "PLBB": 0,
    "PRBB": 0,
    "PLFB": 0,
    "PRFB": 0
  },
  {
    "name": "Template 60",
    "positions": [0, 1, 3, 4, 10, 11, 12],
    "PLSL": 3,
    "PLSR": 3,
    "PLWR": 0,
    "PRWR": 0,
    "PLBB": 0,
    "PRBB": 0,
    "PLFB": 0,
    "PRFB": 0
  },
  {
    "name": "Template 61",
    "positions": [0, 1, 3, 4, 10, 11, 12],
    "PLSL": 3,
    "PLSR": 3,
    "PLWR": 3,
    "PRWR": 3,
    "PLBB": 0,
    "PRBB": 0,
    "PLFB": 0,
    "PRFB": 0
  },
  {
    "name": "Template 62",
    "positions": [0, 1, 3, 4, 10, 11, 12],
    "PLSL": 3,
    "PLSR": 3,
    "PLWR": 10,
    "PRWR": 10,
    "PLBB": 0,
    "PRBB": 0,
    "PLFB": 0,
    "PRFB": 0
  },
  {
    "name": "Template 63",
    "positions": [0, 1, 3, 4, 10, 11, 12],
    "PLSL": 3,
    "PLSR": 3,
    "PLWR": 11,
    "PRWR": 11,
    "PLBB": 0,
    "PRBB": 0,
    "PLFB": 0,
    "PRFB": 0
  },
  {
    "name": "Template 64",
    "positions": [3, 16, 17, 18],
    "PLSL": 4,
    "PLSR": 4,
    "PLWR": 0,
    "PRWR": 0,
    "PLBB": 0,
    "PRBB": 0,
    "PLFB": 0,
    "PRFB": 0
  },
  {
    "name": "Template 65",
    "positions": [3, 16, 17, 18],
    "PLSL": 4,
    "PLSR": 4,
    "PLWR": 0,
    "PRWR": 0,
    "PLBB": 1,
    "PRBB": 1,
    "PLFB": 0,
    "PRFB": 0
  },
  {
    "name": "Template 66",
    "positions": [3, 16, 17, 18],
    "PLSL": 4,
    "PLSR": 4,
    "PLWR": 0,
    "PRWR": 0,
    "PLBB": 3,
    "PRBB": 3,
    "PLFB": 0,
    "PRFB": 0
  },
  {
    "name": "Template 67",
    "positions": [3, 16, 17, 18],
    "PLSL": 6,
    "PLSR": 6,
    "PLWR": 0,
    "PRWR": 0,
    "PLBB": 0,
    "PRBB": 0,
    "PLFB": 0,
    "PRFB": 0
  },
  {
    "name": "Template 68",
    "positions": [3, 16, 17, 18],
    "PLSL": 6,
    "PLSR": 6,
    "PLWR": 0,
    "PRWR": 0,
    "PLBB": 1,
    "PRBB": 1,
    "PLFB": 0,
    "PRFB": 0
  },
  {
    "name": "Template 69",
    "positions": [3, 16, 17, 18],
    "PLSL": 6,
    "PLSR": 6,
    "PLWR": 0,
    "PRWR": 0,
    "PLBB": 3,
    "PRBB": 3,
    "PLFB": 0,
    "PRFB": 0
  },
  {
    "name": "Template 70",
    "positions": [0, 19, 20],
    "PLSL": 7,
    "PLSR": 7,
    "PLWR": 1,
    "PRWR": 1,
    "PLBB": 0,
    "PRBB": 0,
    "PLFB": 0,
    "PRFB": 0
  },
  {
    "name": "Template 71",
    "positions": [1, 3, 17, 18],
    "PLSL": 7,
    "PLSR": 7,
    "PLWR": 1,
    "PRWR": 1,
    "PLBB": 0,
    "PRBB": 0,
    "PLFB": 1,
    "PRFB": 1
  },
  {
    "name": "Template 72",
    "positions": [1, 3, 17, 18],
    "PLSL": 7,
    "PLSR": 7,
    "PLWR": 1,
    "PRWR": 1,
    "PLBB": 0,
    "PRBB": 0,
    "PLFB": 3,
    "PRFB": 3
  },
  {
    "name": "Template 73",
    "positions": [0, 19, 20],
    "PLSL": 7,
    "PLSR": 7,
    "PLWR": 3,
    "PRWR": 3,
    "PLBB": 0,
    "PRBB": 0,
    "PLFB": 0,
    "PRFB": 0
  },
  {
    "name": "Template 74",
    "positions": [1, 3, 17, 18],
    "PLSL": 7,
    "PLSR": 7,
    "PLWR": 3,
    "PRWR": 3,
    "PLBB": 0,
    "PRBB": 0,
    "PLFB": 1,
    "PRFB": 1
  },
  {
    "name": "Template 75",
    "positions": [1, 3, 17, 18],
    "PLSL": 7,
    "PLSR": 7,
    "PLWR": 3,
    "PRWR": 3,
    "PLBB": 0,
    "PRBB": 0,
    "PLFB": 3,
    "PRFB": 3
  },
  {
    "name": "Template 76",
    "positions": [0, 19, 20],
    "PLSL": 7,
    "PLSR": 7,
    "PLWR": 10,
    "PRWR": 10,
    "PLBB": 0,
    "PRBB": 0,
    "PLFB": 0,
    "PRFB": 0
  },
  {
    "name": "Template 77",
    "positions": [1, 3, 17, 18],
    "PLSL": 7,
    "PLSR": 7,
    "PLWR": 10,
    "PRWR": 10,
    "PLBB": 0,
    "PRBB": 0,
    "PLFB": 1,
    "PRFB": 1
  },
  {
    "name": "Template 78",
    "positions": [1, 3, 17, 18],
    "PLSL": 7,
    "PLSR": 7,
    "PLWR": 10,
    "PRWR": 10,
    "PLBB": 0,
    "PRBB": 0,
    "PLFB": 3,
    "PRFB": 3
  },
  {
    "name": "Template 79",
    "positions": [0, 19, 20],
    "PLSL": 7,
    "PLSR": 7,
    "PLWR": 11,
    "PRWR": 11,
    "PLBB": 0,
    "PRBB": 0,
    "PLFB": 0,
    "PRFB": 0
  },
  {
    "name": "Template 80",
    "positions": [1, 3, 17, 18],
    "PLSL": 7,
    "PLSR": 7,
    "PLWR": 11,
    "PRWR": 11,
    "PLBB": 0,
    "PRBB": 0,
    "PLFB": 1,
    "PRFB": 1
  },
  {
    "name": "Template 81",
    "positions": [1, 3, 17, 18],
    "PLSL": 7,
    "PLSR": 7,
    "PLWR": 11,
    "PRWR": 11,
    "PLBB": 0,
    "PRBB": 0,
    "PLFB": 3,
    "PRFB": 3
  },
  {
    "name": "Template 82",
    "positions": [0, 19, 20],
    "PLSL": 9,
    "PLSR": 9,
    "PLWR": 1,
    "PRWR": 1,
    "PLBB": 0,
    "PRBB": 0,
    "PLFB": 0,
    "PRFB": 0
  },
  {
    "name": "Template 83",
    "positions": [1, 3, 17, 18],
    "PLSL": 9,
    "PLSR": 9,
    "PLWR": 1,
    "PRWR": 1,
    "PLBB": 0,
    "PRBB": 0,
    "PLFB": 1,
    "PRFB": 1
  },
  {
    "name": "Template 84",
    "positions": [1, 3, 17, 18],
    "PLSL": 9,
    "PLSR": 9,
    "PLWR": 1,
    "PRWR": 1,
    "PLBB": 0,
    "PRBB": 0,
    "PLFB": 3,
    "PRFB": 3
  },
  {
    "name": "Template 85",
    "positions": [0, 19, 20],
    "PLSL": 9,
    "PLSR": 9,
    "PLWR": 3,
    "PRWR": 3,
    "PLBB": 0,
    "PRBB": 0,
    "PLFB": 0,
    "PRFB": 0
  },
  {
    "name": "Template 86",
    "positions": [1, 3, 17, 18],
    "PLSL": 9,
    "PLSR": 9,
    "PLWR": 3,
    "PRWR": 3,
    "PLBB": 0,
    "PRBB": 0,
    "PLFB": 1,
    "PRFB": 1
  },
  {
    "name": "Template 87",
    "positions": [1, 3, 17, 18],
    "PLSL": 9,
    "PLSR": 9,
    "PLWR": 3,
    "PRWR": 3,
    "PLBB": 0,
    "PRBB": 0,
    "PLFB": 3,
    "PRFB": 3
  },
  {
    "name": "Template 88",
    "positions": [0, 19, 20],
    "PLSL": 9,
    "PLSR": 9,
    "PLWR": 10,
    "PRWR": 10,
    "PLBB": 0,
    "PRBB": 0,
    "PLFB": 0,
    "PRFB": 0
  },
  {
    "name": "Template 89",
    "positions": [1, 3, 17, 18],
    "PLSL": 9,
    "PLSR": 9,
    "PLWR": 10,
    "PRWR": 10,
    "PLBB": 0,
    "PRBB": 0,
    "PLFB": 1,
    "PRFB": 1
  },
  {
    "name": "Template 90",
    "positions": [1, 3, 17, 18],
    "PLSL": 9,
    "PLSR": 9,
    "PLWR": 10,
    "PRWR": 10,
    "PLBB": 0,
    "PRBB": 0,
    "PLFB": 3,
    "PRFB": 3
  },
  {
    "name": "Template 91",
    "positions": [0, 19, 20],
    "PLSL": 9,
    "PLSR": 9,
    "PLWR": 11,
    "PRWR": 11,
    "PLBB": 0,
    "PRBB": 0,
    "PLFB": 0,
    "PRFB": 0
  },
  {
    "name": "Template 92",
    "positions": [1, 3, 17, 18],
    "PLSL": 9,
    "PLSR": 9,
    "PLWR": 11,
    "PRWR": 11,
    "PLBB": 0,
    "PRBB": 0,
    "PLFB": 1,
    "PRFB": 1
  },
  {
    "name": "Template 93",
    "positions": [1, 3, 17, 18],
    "PLSL": 9,
    "PLSR": 9,
    "PLWR": 11,
    "PRWR": 11,
    "PLBB": 0,
    "PRBB": 0,
    "PLFB": 3,
    "PRFB": 3
  },
  {
    "name": "Template 94",
    "positions": [0, 1, 2, 3, 4, 10, 11, 12, 13, 14, 15, 16, 17, 18, 19, 20],
    "PLSL": 10,
    "PLSR": 1,
    "PLWR": 1,
    "PRWR": 1,
    "PLBB": 0,
    "PRBB": 0,
    "PLFB": 0,
    "PRFB": 0
  },
  {
    "name": "Template 95",
    "positions": [1, 3, 4, 10, 11, 13, 14, 15, 16, 17, 18],
    "PLSL": 10,
    "PLSR": 1,
    "PLWR": 1,
    "PRWR": 1,
    "PLBB": 1,
    "PRBB": 0,
    "PLFB": 1,
    "PRFB": 0
  },
  {
    "name": "Template 96",
    "positions": [1, 3, 4, 10, 11, 13, 14, 15, 16, 17, 18],
    "PLSL": 10,
    "PLSR": 1,
    "PLWR": 1,
    "PRWR": 1,
    "PLBB": 3,
    "PRBB": 0,
    "PLFB": 3,
    "PRFB": 0
  },
  {
    "name": "Template 97",
    "positions": [0, 1, 2, 3, 4, 10, 11, 12, 13, 14, 15, 16, 17, 18, 19, 20],
    "PLSL": 10,
    "PLSR": 1,
    "PLWR": 3,
    "PRWR": 3,
    "PLBB": 0,
    "PRBB": 0,
    "PLFB": 0,
    "PRFB": 0
  },
  {
    "name": "Template 98",
    "positions": [1, 3, 4, 10, 11, 13, 14, 15, 16, 17, 18],
    "PLSL": 10,
    "PLSR": 1,
    "PLWR": 3,
    "PRWR": 3,
    "PLBB": 1,
    "PRBB": 0,
    "PLFB": 1,
    "PRFB": 0
  },
  {
    "name": "Template 99",
    "positions": [1, 3, 4, 10, 11, 13, 14, 15, 16, 17, 18],
    "PLSL": 10,
    "PLSR": 1,
    "PLWR": 3,
    "PRWR": 3,
    "PLBB": 3,
    "PRBB": 0,
    "PLFB": 3,
    "PRFB": 0
  },
  {
    "name": "Template 100",
    "positions": [0, 1, 2, 3, 4, 10, 11, 12, 13, 14, 15, 16, 17, 18, 19, 20],
    "PLSL": 10,
    "PLSR": 1,
    "PLWR": 10,
    "PRWR": 10,
    "PLBB": 0,
    "PRBB": 0,
    "PLFB": 0,
    "PRFB": 0
  },
  {
    "name": "Template 101",
    "positions": [1, 3, 4, 10, 11, 13, 14, 15, 16, 17, 18],
    "PLSL": 10,
    "PLSR": 1,
    "PLWR": 10,
    "PRWR": 10,
    "PLBB": 1,
    "PRBB": 0,
    "PLFB": 1,
    "PRFB": 0
  },
  {
    "name": "Template 102",
    "positions": [1, 3, 4, 10, 11, 13, 14, 15, 16, 17, 18],
    "PLSL": 10,
    "PLSR": 1,
    "PLWR": 10,
    "PRWR": 10,
    "PLBB": 3,
    "PRBB": 0,
    "PLFB": 3,
    "PRFB": 0
  },
  {
    "name": "Template 103",
    "positions": [0, 1, 2, 3, 4, 10, 11, 12, 13, 14, 15, 16, 17, 18, 19, 20],
    "PLSL": 10,
    "PLSR": 1,
    "PLWR": 11,
    "PRWR": 11,
    "PLBB": 0,
    "PRBB": 0,
    "PLFB": 0,
    "PRFB": 0
  },
  {
    "name": "Template 104",
    "positions": [1, 3, 4, 10, 11, 13, 14, 15, 16, 17, 18],
    "PLSL": 10,
    "PLSR": 1,
    "PLWR": 11,
    "PRWR": 11,
    "PLBB": 1,
    "PRBB": 0,
    "PLFB": 1,
    "PRFB": 0
  },
  {
    "name": "Template 105",
    "positions": [1, 3, 4, 10, 11, 13, 14, 15, 16, 17, 18],
    "PLSL": 10,
    "PLSR": 1,
    "PLWR": 11,
    "PRWR": 11,
    "PLBB": 3,
    "PRBB": 0,
    "PLFB": 3,
    "PRFB": 0
  },
  {
    "name": "Template 106",
    "positions": [0, 1, 2, 3, 4, 10, 11, 12, 13, 14, 15, 16, 17, 18, 19, 20],
    "PLSL": 12,
    "PLSR": 3,
    "PLWR": 1,
    "PRWR": 1,
    "PLBB": 0,
    "PRBB": 0,
    "PLFB": 0,
    "PRFB": 0
  },
  {
    "name": "Template 107",
    "positions": [1, 3, 4, 10, 11, 13, 14, 15, 16, 17, 18],
    "PLSL": 12,
    "PLSR": 3,
    "PLWR": 1,
    "PRWR": 1,
    "PLBB": 1,
    "PRBB": 0,
    "PLFB": 1,
    "PRFB": 0
  },
  {
    "name": "Template 108",
    "positions": [1, 3, 4, 10, 11, 13, 14, 15, 16, 17, 18],
    "PLSL": 12,
    "PLSR": 3,
    "PLWR": 1,
    "PRWR": 1,
    "PLBB": 3,
    "PRBB": 0,
    "PLFB": 3,
    "PRFB": 0
  },
  {
    "name": "Template 109",
    "positions": [0, 1, 2, 3, 4, 10, 11, 12, 13, 14, 15, 16, 17, 18, 19, 20],
    "PLSL": 12,
    "PLSR": 3,
    "PLWR": 3,
    "PRWR": 3,
    "PLBB": 0,
    "PRBB": 0,
    "PLFB": 0,
    "PRFB": 0
  },
  {
    "name": "Template 110",
    "positions": [1, 3, 4, 10, 11, 13, 14, 15, 16, 17, 18],
    "PLSL": 12,
    "PLSR": 3,
    "PLWR": 3,
    "PRWR": 3,
    "PLBB": 1,
    "PRBB": 0,
    "PLFB": 1,
    "PRFB": 0
  },
  {
    "name": "Template 111",
    "positions": [1, 3, 4, 10, 11, 13, 14, 15, 16, 17, 18],
    "PLSL": 12,
    "PLSR": 3,
    "PLWR": 3,
    "PRWR": 3,
    "PLBB": 3,
    "PRBB": 0,
    "PLFB": 3,
    "PRFB": 0
  },
  {
    "name": "Template 112",
    "positions": [0, 1, 2, 3, 4, 10, 11, 12, 13, 14, 15, 16, 17, 18, 19, 20],
    "PLSL": 12,
    "PLSR": 3,
    "PLWR": 10,
    "PRWR": 10,
    "PLBB": 0,
    "PRBB": 0,
    "PLFB": 0,
    "PRFB": 0
  },
  {
    "name": "Template 113",
    "positions": [1, 3, 4, 10, 11, 13, 14, 15, 16, 17, 18],
    "PLSL": 12,
    "PLSR": 3,
    "PLWR": 10,
    "PRWR": 10,
    "PLBB": 1,
    "PRBB": 0,
    "PLFB": 1,
    "PRFB": 0
  },
  {
    "name": "Template 114",
    "positions": [1, 3, 4, 10, 11, 13, 14, 15, 16, 17, 18],
    "PLSL": 12,
    "PLSR": 3,
    "PLWR": 10,
    "PRWR": 10,
    "PLBB": 3,
    "PRBB": 0,
    "PLFB": 3,
    "PRFB": 0
  },
  {
    "name": "Template 115",
    "positions": [0, 1, 2, 3, 4, 10, 11, 12, 13, 14, 15, 16, 17, 18, 19, 20],
    "PLSL": 12,
    "PLSR": 3,
    "PLWR": 11,
    "PRWR": 11,
    "PLBB": 0,
    "PRBB": 0,
    "PLFB": 0,
    "PRFB": 0
  },
  {
    "name": "Template 116",
    "positions": [1, 3, 4, 10, 11, 13, 14, 15, 16, 17, 18],
    "PLSL": 12,
    "PLSR": 3,
    "PLWR": 11,
    "PRWR": 11,
    "PLBB": 1,
    "PRBB": 0,
    "PLFB": 1,
    "PRFB": 0
  },
  {
    "name": "Template 117",
    "positions": [1, 3, 4, 10, 11, 13, 14, 15, 16, 17, 18],
    "PLSL": 12,
    "PLSR": 3,
    "PLWR": 11,
    "PRWR": 11,
    "PLBB": 3,
    "PRBB": 0,
    "PLFB": 3,
    "PRFB": 0
  },
  {
    "name": "Template 118",
    "positions": [0, 1, 2, 3, 4, 10, 11, 12, 13, 14, 15, 16, 17, 18, 19, 20],
    "PLSL": 1,
    "PLSR": 10,
    "PLWR": 1,
    "PRWR": 1,
    "PLBB": 0,
    "PRBB": 0,
    "PLFB": 0,
    "PRFB": 0
  },
  {
    "name": "Template 119",
    "positions": [1, 3, 4, 10, 11, 13, 14, 15, 16, 17, 18],
    "PLSL": 1,
    "PLSR": 10,
    "PLWR": 1,
    "PRWR": 1,
    "PLBB": 0,
    "PRBB": 1,
    "PLFB": 0,
    "PRFB": 1
  },
  {
    "name": "Template 120",
    "positions": [1, 3, 4, 10, 11, 13, 14, 15, 16, 17, 18],
    "PLSL": 1,
    "PLSR": 10,
    "PLWR": 1,
    "PRWR": 1,
    "PLBB": 0,
    "PRBB": 3,
    "PLFB": 0,
    "PRFB": 3
  },
  {
    "name": "Template 121",
    "positions": [0, 1, 2, 3, 4, 10, 11, 12, 13, 14, 15, 16, 17, 18, 19, 20],
    "PLSL": 1,
    "PLSR": 10,
    "PLWR": 3,
    "PRWR": 3,
    "PLBB": 0,
    "PRBB": 0,
    "PLFB": 0,
    "PRFB": 0
  },
  {
    "name": "Template 122",
    "positions": [1, 3, 4, 10, 11, 13, 14, 15, 16, 17, 18],
    "PLSL": 1,
    "PLSR": 10,
    "PLWR": 3,
    "PRWR": 3,
    "PLBB": 0,
    "PRBB": 1,
    "PLFB": 0,
    "PRFB": 1
  },
  {
    "name": "Template 123",
    "positions": [1, 3, 4, 10, 11, 13, 14, 15, 16, 17, 18],
    "PLSL": 1,
    "PLSR": 10,
    "PLWR": 3,
    "PRWR": 3,
    "PLBB": 0,
    "PRBB": 3,
    "PLFB": 0,
    "PRFB": 3
  },
  {
    "name": "Template 124",
    "positions": [0, 1, 2, 3, 4, 10, 11, 12, 13, 14, 15, 16, 17, 18, 19, 20],
    "PLSL": 1,
    "PLSR": 10,
    "PLWR": 10,
    "PRWR": 10,
    "PLBB": 0,
    "PRBB": 0,
    "PLFB": 0,
    "PRFB": 0
  },
  {
    "name": "Template 125",
    "positions": [1, 3, 4, 10, 11, 13, 14, 15, 16, 17, 18],
    "PLSL": 1,
    "PLSR": 10,
    "PLWR": 10,
    "PRWR": 10,
    "PLBB": 0,
    "PRBB": 1,
    "PLFB": 0,
    "PRFB": 1
  },
  {
    "name": "Template 126",
    "positions": [1, 3, 4, 10, 11, 13, 14, 15, 16, 17, 18],
    "PLSL": 1,
    "PLSR": 10,
    "PLWR": 10,
    "PRWR": 10,
    "PLBB": 0,
    "PRBB": 3,
    "PLFB": 0,
    "PRFB": 3
  },
  {
    "name": "Template 127",
    "positions": [0, 1, 2, 3, 4, 10, 11, 12, 13, 14, 15, 16, 17, 18, 19, 20],
    "PLSL": 1,
    "PLSR": 10,
    "PLWR": 11,
    "PRWR": 11,
    "PLBB": 0,
    "PRBB": 0,
    "PLFB": 0,
    "PRFB": 0
  },
  {
    "name": "Template 128",
    "positions": [1, 3, 4, 10, 11, 13, 14, 15, 16, 17, 18],
    "PLSL": 1,
    "PLSR": 10,
    "PLWR": 11,
    "PRWR": 11,
    "PLBB": 0,
    "PRBB": 1,
    "PLFB": 0,
    "PRFB": 1
  },
  {
    "name": "Template 129",
    "positions": [1, 3, 4, 10, 11, 13, 14, 15, 16, 17, 18],
    "PLSL": 1,
    "PLSR": 10,
    "PLWR": 11,
    "PRWR": 11,
    "PLBB": 0,
    "PRBB": 3,
    "PLFB": 0,
    "PRFB": 3
  },
  {
    "name": "Template 130",
    "positions": [0, 1, 2, 3, 4, 10, 11, 12, 13, 14, 15, 16, 17, 18, 19, 20],
    "PLSL": 3,
    "PLSR": 12,
    "PLWR": 1,
    "PRWR": 1,
    "PLBB": 0,
    "PRBB": 0,
    "PLFB": 0,
    "PRFB": 0
  },
  {
    "name": "Template 131",
    "positions": [1, 3, 4, 10, 11, 13, 14, 15, 16, 17, 18],
    "PLSL": 3,
    "PLSR": 12,
    "PLWR": 1,
    "PRWR": 1,
    "PLBB": 0,
    "PRBB": 1,
    "PLFB": 0,
    "PRFB": 1
  },
  {
    "name": "Template 132",
    "positions": [1, 3, 4, 10, 11, 13, 14, 15, 16, 17, 18],
    "PLSL": 3,
    "PLSR": 12,
    "PLWR": 1,
    "PRWR": 1,
    "PLBB": 0,
    "PRBB": 3,
    "PLFB": 0,
    "PRFB": 3
  },
  {
    "name": "Template 133",
    "positions": [0, 1, 2, 3, 4, 10, 11, 12, 13, 14, 15, 16, 17, 18, 19, 20],
    "PLSL": 3,
    "PLSR": 12,
    "PLWR": 3,
    "PRWR": 3,
    "PLBB": 0,
    "PRBB": 0,
    "PLFB": 0,
    "PRFB": 0
  },
  {
    "name": "Template 134",
    "positions": [1, 3, 4, 10, 11, 13, 14, 15, 16, 17, 18],
    "PLSL": 3,
    "PLSR": 12,
    "PLWR": 3,
    "PRWR": 3,
    "PLBB": 0,
    "PRBB": 1,
    "PLFB": 0,
    "PRFB": 1
  },
  {
    "name": "Template 135",
    "positions": [1, 3, 4, 10, 11, 13, 14, 15, 16, 17, 18],
    "PLSL": 3,
    "PLSR": 12,
    "PLWR": 3,
    "PRWR": 3,
    "PLBB": 0,
    "PRBB": 3,
    "PLFB": 0,
    "PRFB": 3
  },
  {
    "name": "Template 136",
    "positions": [0, 1, 2, 3, 4, 10, 11, 12, 13, 14, 15, 16, 17, 18, 19, 20],
    "PLSL": 3,
    "PLSR": 12,
    "PLWR": 10,
    "PRWR": 10,
    "PLBB": 0,
    "PRBB": 0,
    "PLFB": 0,
    "PRFB": 0
  },
  {
    "name": "Template 137",
    "positions": [1, 3, 4, 10, 11, 13, 14, 15, 16, 17, 18],
    "PLSL": 3,
    "PLSR": 12,
    "PLWR": 10,
    "PRWR": 10,
    "PLBB": 0,
    "PRBB": 1,
    "PLFB": 0,
    "PRFB": 1
  },
  {
    "name": "Template 138",
    "positions": [1, 3, 4, 10, 11, 13, 14, 15, 16, 17, 18],
    "PLSL": 3,
    "PLSR": 12,
    "PLWR": 10,
    "PRWR": 10,
    "PLBB": 0,
    "PRBB": 3,
    "PLFB": 0,
    "PRFB": 3
  },
  {
    "name": "Template 139",
    "positions": [0, 1, 2, 3, 4, 10, 11, 12, 13, 14, 15, 16, 17, 18, 19, 20],
    "PLSL": 3,
    "PLSR": 12,
    "PLWR": 11,
    "PRWR": 11,
    "PLBB": 0,
    "PRBB": 0,
    "PLFB": 0,
    "PRFB": 0
  },
  {
    "name": "Template 140",
    "positions": [1, 3, 4, 10, 11, 13, 14, 15, 16, 17, 18],
    "PLSL": 3,
    "PLSR": 12,
    "PLWR": 11,
    "PRWR": 11,
    "PLBB": 0,
    "PRBB": 1,
    "PLFB": 0,
    "PRFB": 1
  },
  {
    "name": "Template 141",
    "positions": [1, 3, 4, 10, 11, 13, 14, 15, 16, 17, 18],
    "PLSL": 3,
    "PLSR": 12,
    "PLWR": 11,
    "PRWR": 11,
    "PLBB": 0,
    "PRBB": 3,
    "PLFB": 0,
    "PRFB": 3
  },
  {
    "name": "Template 142",
    "positions": [0, 19, 20],
    "PLSL": 10,
    "PLSR": 10,
    "PLWR": 0,
    "PRWR": 0,
    "PLBB": 0,
    "PRBB": 0,
    "PLFB": 0,
    "PRFB": 0
  },
  {
    "name": "Template 143",
    "positions": [1, 3, 4, 13, 14, 15, 16, 17, 18],
    "PLSL": 10,
    "PLSR": 10,
    "PLWR": 0,
    "PRWR": 0,
    "PLBB": 1,
    "PRBB": 1,
    "PLFB": 1,
    "PRFB": 1
  },
  {
    "name": "Template 144",
    "positions": [1, 3, 4, 13, 14, 15, 16, 17, 18],
    "PLSL": 10,
    "PLSR": 10,
    "PLWR": 0,
    "PRWR": 0,
    "PLBB": 3,
    "PRBB": 3,
    "PLFB": 3,
    "PRFB": 3
  },
  {
    "name": "Template 145",
    "positions": [0, 19, 20],
    "PLSL": 10,
    "PLSR": 10,
    "PLWR": 1,
    "PRWR": 1,
    "PLBB": 0,
    "PRBB": 0,
    "PLFB": 0,
    "PRFB": 0
  },
  {
    "name": "Template 146",
    "positions": [1, 3, 4, 13, 14, 15, 16, 17, 18],
    "PLSL": 10,
    "PLSR": 10,
    "PLWR": 1,
    "PRWR": 1,
    "PLBB": 1,
    "PRBB": 1,
    "PLFB": 1,
    "PRFB": 1
  },
  {
    "name": "Template 147",
    "positions": [1, 3, 4, 13, 14, 15, 16, 17, 18],
    "PLSL": 10,
    "PLSR": 10,
    "PLWR": 1,
    "PRWR": 1,
    "PLBB": 3,
    "PRBB": 3,
    "PLFB": 3,
    "PRFB": 3
  },
  {
    "name": "Template 148",
    "positions": [0, 19, 20],
    "PLSL": 10,
    "PLSR": 10,
    "PLWR": 3,
    "PRWR": 3,
    "PLBB": 0,
    "PRBB": 0,
    "PLFB": 0,
    "PRFB": 0
  },
  {
    "name": "Template 149",
    "positions": [1, 3, 4, 13, 14, 15, 16, 17, 18],
    "PLSL": 10,
    "PLSR": 10,
    "PLWR": 3,
    "PRWR": 3,
    "PLBB": 1,
    "PRBB": 1,
    "PLFB": 1,
    "PRFB": 1
  },
  {
    "name": "Template 150",
    "positions": [1, 3, 4, 13, 14, 15, 16, 17, 18],
    "PLSL": 10,
    "PLSR": 10,
    "PLWR": 3,
    "PRWR": 3,
    "PLBB": 3,
    "PRBB": 3,
    "PLFB": 3,
    "PRFB": 3
  },
  {
    "name": "Template 151",
    "positions": [0, 19, 20],
    "PLSL": 10,
    "PLSR": 10,
    "PLWR": 4,
    "PRWR": 4,
    "PLBB": 0,
    "PRBB": 0,
    "PLFB": 0,
    "PRFB": 0
  },
  {
    "name": "Template 152",
    "positions": [1, 3, 4, 13, 14, 15, 16, 17, 18],
    "PLSL": 10,
    "PLSR": 10,
    "PLWR": 4,
    "PRWR": 4,
    "PLBB": 1,
    "PRBB": 1,
    "PLFB": 1,
    "PRFB": 1
  },
  {
    "name": "Template 153",
    "positions": [1, 3, 4, 13, 14, 15, 16, 17, 18],
    "PLSL": 10,
    "PLSR": 10,
    "PLWR": 4,
    "PRWR": 4,
    "PLBB": 3,
    "PRBB": 3,
    "PLFB": 3,
    "PRFB": 3
  },
  {
    "name": "Template 154",
    "positions": [0, 19, 20],
    "PLSL": 10,
    "PLSR": 10,
    "PLWR": 6,
    "PRWR": 6,
    "PLBB": 0,
    "PRBB": 0,
    "PLFB": 0,
    "PRFB": 0
  },
  {
    "name": "Template 155",
    "positions": [1, 3, 4, 13, 14, 15, 16, 17, 18],
    "PLSL": 10,
    "PLSR": 10,
    "PLWR": 6,
    "PRWR": 6,
    "PLBB": 1,
    "PRBB": 1,
    "PLFB": 1,
    "PRFB": 1
  },
  {
    "name": "Template 156",
    "positions": [1, 3, 4, 13, 14, 15, 16, 17, 18],
    "PLSL": 10,
    "PLSR": 10,
    "PLWR": 6,
    "PRWR": 6,
    "PLBB": 3,
    "PRBB": 3,
    "PLFB": 3,
    "PRFB": 3
  },
  {
    "name": "Template 157",
    "positions": [0, 19, 20],
    "PLSL": 12,
    "PLSR": 12,
    "PLWR": 0,
    "PRWR": 0,
    "PLBB": 0,
    "PRBB": 0,
    "PLFB": 0,
    "PRFB": 0
  },
  {
    "name": "Template 158",
    "positions": [1, 3, 4, 13, 14, 15, 16, 17, 18],
    "PLSL": 12,
    "PLSR": 12,
    "PLWR": 0,
    "PRWR": 0,
    "PLBB": 1,
    "PRBB": 1,
    "PLFB": 1,
    "PRFB": 1
  },
  {
    "name": "Template 159",
    "positions": [1, 3, 4, 13, 14, 15, 16, 17, 18],
    "PLSL": 12,
    "PLSR": 12,
    "PLWR": 0,
    "PRWR": 0,
    "PLBB": 3,
    "PRBB": 3,
    "PLFB": 3,
    "PRFB": 3
  },
  {
    "name": "Template 160",
    "positions": [0, 19, 20],
    "PLSL": 12,
    "PLSR": 12,
    "PLWR": 1,
    "PRWR": 1,
    "PLBB": 0,
    "PRBB": 0,
    "PLFB": 0,
    "PRFB": 0
  },
  {
    "name": "Template 161",
    "positions": [1, 3, 4, 13, 14, 15, 16, 17, 18],
    "PLSL": 12,
    "PLSR": 12,
    "PLWR": 1,
    "PRWR": 1,
    "PLBB": 1,
    "PRBB": 1,
    "PLFB": 1,
    "PRFB": 1
  },
  {
    "name": "Template 162",
    "positions": [1, 3, 4, 13, 14, 15, 16, 17, 18],
    "PLSL": 12,
    "PLSR": 12,
    "PLWR": 1,
    "PRWR": 1,
    "PLBB": 3,
    "PRBB": 3,
    "PLFB": 3,
    "PRFB": 3
  },
  {
    "name": "Template 163",
    "positions": [0, 19, 20],
    "PLSL": 12,
    "PLSR": 12,
    "PLWR": 3,
    "PRWR": 3,
    "PLBB": 0,
    "PRBB": 0,
    "PLFB": 0,
    "PRFB": 0
  },
  {
    "name": "Template 164",
    "positions": [1, 3, 4, 13, 14, 15, 16, 17, 18],
    "PLSL": 12,
    "PLSR": 12,
    "PLWR": 3,
    "PRWR": 3,
    "PLBB": 1,
    "PRBB": 1,
    "PLFB": 1,
    "PRFB": 1
  },
  {
    "name": "Template 165",
    "positions": [1, 3, 4, 13, 14, 15, 16, 17, 18],
    "PLSL": 12,
    "PLSR": 12,
    "PLWR": 3,
    "PRWR": 3,
    "PLBB": 3,
    "PRBB": 3,
    "PLFB": 3,
    "PRFB": 3
  },
  {
    "name": "Template 166",
    "positions": [0, 19, 20],
    "PLSL": 12,
    "PLSR": 12,
    "PLWR": 4,
    "PRWR": 4,
    "PLBB": 0,
    "PRBB": 0,
    "PLFB": 0,
    "PRFB": 0
  },
  {
    "name": "Template 167",
    "positions": [1, 3, 4, 13, 14, 15, 16, 17, 18],
    "PLSL": 12,
    "PLSR": 12,
    "PLWR": 4,
    "PRWR": 4,
    "PLBB": 1,
    "PRBB": 1,
    "PLFB": 1,
    "PRFB": 1
  },
  {
    "name": "Template 168",
    "positions": [1, 3, 4, 13, 14, 15, 16, 17, 18],
    "PLSL": 12,
    "PLSR": 12,
    "PLWR": 4,
    "PRWR": 4,
    "PLBB": 3,
    "PRBB": 3,
    "PLFB": 3,
    "PRFB": 3
  },
  {
    "name": "Template 169",
    "positions": [0, 19, 20],
    "PLSL": 12,
    "PLSR": 12,
    "PLWR": 6,
    "PRWR": 6,
    "PLBB": 0,
    "PRBB": 0,
    "PLFB": 0,
    "PRFB": 0
  },
  {
    "name": "Template 170",
    "positions": [1, 3, 4, 13, 14, 15, 16, 17, 18],
    "PLSL": 12,
    "PLSR": 12,
    "PLWR": 6,
    "PRWR": 6,
    "PLBB": 1,
    "PRBB": 1,
    "PLFB": 1,
    "PRFB": 1
  },
  {
    "name": "Template 171",
    "positions": [1, 3, 4, 13, 14, 15, 16, 17, 18],
    "PLSL": 12,
    "PLSR": 12,
    "PLWR": 6,
    "PRWR": 6,
    "PLBB": 3,
    "PRBB": 3,
    "PLFB": 3,
    "PRFB": 3
  }
]
